{
  "D1": "10",
  "D2": "1",
  "D3": "10363881595_REMH020203359",
  "rfc": "REMH020203359",
  "curp": "REMH020203HMCYRBA4",
  "nombre": "HEBER",
  "apellido_paterno": "REYES",
  "apellido_materno": "MARTINEZ",
  "fecha_nacimiento": "03-02-2002",
  "fecha_inicio_operaciones": "02-07-2020",
  "situacion_contribuyente": "ACTIVO",
  "fecha_ultimo_cambio": "02-07-2020",
  "regimen": "Régimen de Sueldos y Salarios e Ingresos Asimilados a Salarios",
  "fecha_alta": "02-07-2020",
  "entidad": "MÉXICO",
  "municipio": "VILLA VICTORIA",
  "colonia": "EL CERRILLO",
  "tipo_vialidad": "CALLE",
  "nombre_vialidad": "SIN NOMBRE",
  "numero_exterior": "269",
  "numero_interior": "",
  "cp": "50995",
  "correo": "",
  "al": "MÉXICO 1",
  "RFC_ETIQUETA": "REMH020203359",
  "NOMBRE_ETIQUETA": "HEBER REYES MARTINEZ",
  "IDCIF_ETIQUETA": "10363881595"
}