{
  "D1": "10",
  "D2": "1",
  "D3": "11159847663_AOOR790508U36",
  "rfc": "AOOR790508U36",
  "curp": "AOOR790508MDFLRY04",
  "nombre": "REYNA ELIZABETH",
  "apellido_paterno": "ALONSO",
  "apellido_materno": "ORTA",
  "fecha_nacimiento": "08-05-1979",
  "fecha_inicio_operaciones": "09-07-1997",
  "situacion_contribuyente": "ACTIVO",
  "fecha_ultimo_cambio": "09-07-1997",
  "regimen": "Régimen de Sueldos y Salarios e Ingresos Asimilados a Salarios",
  "fecha_alta": "09-07-1997",
  "entidad": "DISTRITO FEDERAL",
  "municipio": "GUSTAVO A MADERO",
  "colonia": "",
  "tipo_vialidad": "CALLE",
  "nombre_vialidad": "SIN NOMBRE",
  "numero_exterior": "402",
  "numero_interior": "",
  "cp": "",
  "correo": "",
  "al": "DISTRITO FEDERAL 1",
  "RFC_ETIQUETA": "AOOR790508U36",
  "NOMBRE_ETIQUETA": "REYNA ELIZABETH ALONSO ORTA",
  "IDCIF_ETIQUETA": "11159847663"
}