{
  "D1": "10",
  "D2": "1",
  "D3": "11831760664_JILM751031RC4",
  "rfc": "JILM751031RC4",
  "curp": "JILM751031HGRMBG04",
  "nombre": "MIGUEL ANGEL",
  "apellido_paterno": "JIMENEZ",
  "apellido_materno": "LIBORIO",
  "fecha_nacimiento": "31-10-1975",
  "fecha_inicio_operaciones": "22-05-1991",
  "situacion_contribuyente": "ACTIVO",
  "fecha_ultimo_cambio": "22-05-1991",
  "regimen": "Régimen de Sueldos y Salarios e Ingresos Asimilados a Salarios",
  "fecha_alta": "22-05-1991",
  "entidad": "GUERRERO",
  "municipio": "CUAJINICUILAPA",
  "colonia": "LA BANDA",
  "tipo_vialidad": "CALLE",
  "nombre_vialidad": "SIN NOMBRE",
  "numero_exterior": "55",
  "numero_interior": "",
  "cp": "41947",
  "correo": "",
  "al": "GUERRERO 1",
  "RFC_ETIQUETA": "JILM751031RC4",
  "NOMBRE_ETIQUETA": "MIGUEL ANGEL JIMENEZ LIBORIO",
  "IDCIF_ETIQUETA": "11831760664"
}