{
  "D1": "10",
  "D2": "1",
  "D3": "11865690687_JEAJ6105032X9",
  "rfc": "JEAJ6105032X9",
  "curp": "JEAJ610503HVZSBV05",
  "nombre": "JUVENAL",
  "apellido_paterno": "DE JESUS",
  "apellido_materno": "ABAD",
  "fecha_nacimiento": "03-05-1961",
  "fecha_inicio_operaciones": "15-12-1977",
  "situacion_contribuyente": "ACTIVO",
  "fecha_ultimo_cambio": "15-12-1977",
  "regimen": "Régimen de Sueldos y Salarios e Ingresos Asimilados a Salarios",
  "fecha_alta": "15-12-1977",
  "entidad": "VERACRUZ DE IGNACIO DE LA LLAVE",
  "municipio": "ALTOTONGA",
  "colonia": "ADOLFO MORENO",
  "tipo_vialidad": "CALLE",
  "nombre_vialidad": "SIN NOMBRE",
  "numero_exterior": "563",
  "numero_interior": "",
  "cp": "93730",
  "correo": "",
  "al": "VERACRUZ DE IGNACIO DE LA LLAVE 1",
  "RFC_ETIQUETA": "JEAJ6105032X9",
  "NOMBRE_ETIQUETA": "JUVENAL DE JESUS ABAD",
  "IDCIF_ETIQUETA": "11865690687"
}