{
  "D1": "10",
  "D2": "1",
  "D3": "12359604315_PAMJ9605242N6",
  "rfc": "PAMJ9605242N6",
  "curp": "PAMJ960524HMCTRN07",
  "nombre": "JONATHAN",
  "apellido_paterno": "PATLAN",
  "apellido_materno": "MORALES",
  "fecha_nacimiento": "24-05-1996",
  "fecha_inicio_operaciones": "30-01-2014",
  "situacion_contribuyente": "ACTIVO",
  "fecha_ultimo_cambio": "30-01-2014",
  "regimen": "Régimen de Sueldos y Salarios e Ingresos Asimilados a Salarios",
  "fecha_alta": "30-01-2014",
  "entidad": "MÉXICO",
  "municipio": "CUAUTITLÁN",
  "colonia": "SAN MATEO IXTACALCO FRACCIÓN TLAXCULPAS",
  "tipo_vialidad": "CALLE",
  "nombre_vialidad": "SIN NOMBRE",
  "numero_exterior": "883",
  "numero_interior": "",
  "cp": "54860",
  "correo": "",
  "al": "MÉXICO 1",
  "RFC_ETIQUETA": "PAMJ9605242N6",
  "NOMBRE_ETIQUETA": "JONATHAN PATLAN MORALES",
  "IDCIF_ETIQUETA": "12359604315"
}