{
  "D1": "10",
  "D2": "1",
  "D3": "14070367778_LERJ740127NE2",
  "rfc": "LERJ740127NE2",
  "curp": "LERJ740127HGTLYM08",
  "nombre": "JAIME",
  "apellido_paterno": "LEAL",
  "apellido_materno": "RAYA",
  "fecha_nacimiento": "",
  "fecha_inicio_operaciones": "",
  "situacion_contribuyente": "SUSPENDIDO",
  "fecha_ultimo_cambio": "",
  "regimen": "",
  "fecha_alta": "",
  "entidad": "BAJA CALIFORNIA",
  "municipio": "TIJUANA",
  "colonia": "",
  "tipo_vialidad": "",
  "nombre_vialidad": "PINO SUAREZ",
  "numero_exterior": "15424",
  "numero_interior": "",
  "cp": "22000",
  "correo": "",
  "al": "",
  "RFC_ETIQUETA": "LERJ740127NE2",
  "NOMBRE_ETIQUETA": "JAIME LEAL RAYA",
  "IDCIF_ETIQUETA": "14070367778"
}