{
  "D1": "10",
  "D2": "1",
  "D3": "14080838900_EURJ630522AM2",
  "rfc": "EURJ630522AM2",
  "curp": "EURJ630522HASSYR03",
  "nombre": "JORGE ALBERTO",
  "apellido_paterno": "ESQUIVEL",
  "apellido_materno": "REYNA",
  "fecha_nacimiento": "",
  "fecha_inicio_operaciones": "",
  "situacion_contribuyente": "REACTIVADO",
  "fecha_ultimo_cambio": "",
  "regimen": "Régimen de Ingresos por Dividendos (socios y accionistas)",
  "fecha_alta": "",
  "entidad": "AGUASCALIENTES",
  "municipio": "AGUASCALIENTES",
  "colonia": "LAS HADAS",
  "tipo_vialidad": "BOULEVARD (BLVD.)",
  "nombre_vialidad": "BLVD A ZACATECAS NORTE",
  "numero_exterior": "501",
  "numero_interior": "B",
  "cp": "20140",
  "correo": "",
  "al": "",
  "RFC_ETIQUETA": "EURJ630522AM2",
  "NOMBRE_ETIQUETA": "JORGE ALBERTO ESQUIVEL REYNA",
  "IDCIF_ETIQUETA": "14080838900"
}