{
  "D1": "10",
  "D2": "1",
  "D3": "14100568248_GEEM9610118F8",
  "rfc": "GEEM9610118F8",
  "curp": "GEEM961011MMCRSN08",
  "nombre": "MONICA PAULINA",
  "apellido_paterno": "GERMAN",
  "apellido_materno": "ESCOBAR",
  "fecha_nacimiento": "",
  "fecha_inicio_operaciones": "",
  "situacion_contribuyente": "ACTIVO",
  "fecha_ultimo_cambio": "",
  "regimen": "Régimen de Sueldos y Salarios e Ingresos Asimilados a Salarios",
  "fecha_alta": "",
  "entidad": "MEXICO",
  "municipio": "CHAPA DE MOTA",
  "colonia": "",
  "tipo_vialidad": "",
  "nombre_vialidad": "DOMICILIO CONOCIDO",
  "numero_exterior": "100",
  "numero_interior": "",
  "cp": "54350",
  "correo": "",
  "al": "",
  "RFC_ETIQUETA": "GEEM9610118F8",
  "NOMBRE_ETIQUETA": "MONICA PAULINA GERMAN ESCOBAR",
  "IDCIF_ETIQUETA": "14100568248"
}