{
  "D1": "10",
  "D2": "1",
  "D3": "14120252947_LOCA951203IV3",
  "rfc": "LOCA951203IV3",
  "curp": "LXCA951203HJCPML08",
  "nombre": "ALDO YARET",
  "apellido_paterno": "LOPEZ",
  "apellido_materno": "CAMACHO",
  "fecha_nacimiento": "",
  "fecha_inicio_operaciones": "",
  "situacion_contribuyente": "ACTIVO",
  "fecha_ultimo_cambio": "",
  "regimen": "Régimen de Sueldos y Salarios e Ingresos Asimilados a Salarios",
  "fecha_alta": "",
  "entidad": "JALISCO",
  "municipio": "EL SALTO",
  "colonia": "LAS PINTITAS CENTRO",
  "tipo_vialidad": "CALLE",
  "nombre_vialidad": "RIO BLANCO",
  "numero_exterior": "45",
  "numero_interior": "",
  "cp": "45693",
  "correo": "",
  "al": "",
  "RFC_ETIQUETA": "LOCA951203IV3",
  "NOMBRE_ETIQUETA": "ALDO YARET LOPEZ CAMACHO",
  "IDCIF_ETIQUETA": "14120252947"
}