{
  "D1": "10",
  "D2": "1",
  "D3": "14120128204_BECB880427B75",
  "rfc": "BECB880427B75",
  "curp": "BECB880427MCSDRL00",
  "nombre": "BLANCA AIDA",
  "apellido_paterno": "BEDRAN",
  "apellido_materno": "DEL CARPIO",
  "fecha_nacimiento": "",
  "fecha_inicio_operaciones": "",
  "situacion_contribuyente": "ACTIVO",
  "fecha_ultimo_cambio": "",
  "regimen": "Sin obligaciones fiscales",
  "fecha_alta": "",
  "entidad": "CHIAPAS",
  "municipio": "JITOTOL",
  "colonia": "CENTRO",
  "tipo_vialidad": "",
  "nombre_vialidad": "3A OTE",
  "numero_exterior": "S/N",
  "numero_interior": "",
  "cp": "29760",
  "correo": "",
  "al": "",
  "RFC_ETIQUETA": "BECB880427B75",
  "NOMBRE_ETIQUETA": "BLANCA AIDA BEDRAN DEL CARPIO",
  "IDCIF_ETIQUETA": "14120128204"
}