{
  "D1": "10",
  "D2": "1",
  "D3": "15080421841_COTE840623MXA",
  "rfc": "COTE840623MXA",
  "curp": "COTE840623HVZXZL09",
  "nombre": "ELISEO",
  "apellido_paterno": "COXCAHUA",
  "apellido_materno": "TZONTEHUA",
  "fecha_nacimiento": "",
  "fecha_inicio_operaciones": "",
  "situacion_contribuyente": "ACTIVO",
  "fecha_ultimo_cambio": "",
  "regimen": "Sin obligaciones fiscales",
  "fecha_alta": "",
  "entidad": "VERACRUZ DE IGNACIO DE LA LLAVE",
  "municipio": "ATLAHUILCO",
  "colonia": "OTRA NO ESPECIFICADA EN EL CATALOGO",
  "tipo_vialidad": "CAMINO",
  "nombre_vialidad": "CONOCIDO",
  "numero_exterior": "SN",
  "numero_interior": "SN",
  "cp": "94830",
  "correo": "",
  "al": "",
  "RFC_ETIQUETA": "COTE840623MXA",
  "NOMBRE_ETIQUETA": "ELISEO COXCAHUA TZONTEHUA",
  "IDCIF_ETIQUETA": "15080421841"
}