{
  "D1": "10",
  "D2": "1",
  "D3": "15100119027_NUFL9606179F8",
  "rfc": "NUFL9606179F8",
  "curp": "NUFL960617HMCXJS06",
  "nombre": "LUIS FERNANDO",
  "apellido_paterno": "NUÑEZ",
  "apellido_materno": "FAJARDO",
  "fecha_nacimiento": "",
  "fecha_inicio_operaciones": "",
  "situacion_contribuyente": "ACTIVO",
  "fecha_ultimo_cambio": "",
  "regimen": "Régimen de Sueldos y Salarios e Ingresos Asimilados a Salarios",
  "fecha_alta": "",
  "entidad": "MEXICO",
  "municipio": "ECATEPEC DE MORELOS",
  "colonia": "LA AGUITA",
  "tipo_vialidad": "CALLE",
  "nombre_vialidad": "CASA VIEJA",
  "numero_exterior": "MANZANA 32 LOTE 62",
  "numero_interior": "SIN NUMERO",
  "cp": "55518",
  "correo": "",
  "al": "",
  "RFC_ETIQUETA": "NUFL9606179F8",
  "NOMBRE_ETIQUETA": "LUIS FERNANDO NUÑEZ FAJARDO",
  "IDCIF_ETIQUETA": "15100119027"
}