{
  "D1": "10",
  "D2": "1",
  "D3": "15110155053_RAFA900621CVA",
  "rfc": "RAFA900621CVA",
  "curp": "RAFA900621HTLMLL06",
  "nombre": "ALEJANDRO",
  "apellido_paterno": "RAMIREZ",
  "apellido_materno": "FLORES",
  "fecha_nacimiento": "",
  "fecha_inicio_operaciones": "",
  "situacion_contribuyente": "ACTIVO",
  "fecha_ultimo_cambio": "",
  "regimen": "Sin obligaciones fiscales",
  "fecha_alta": "",
  "entidad": "TAMAULIPAS",
  "municipio": "NUEVO LAREDO",
  "colonia": "FRACC LOS FRESNOS",
  "tipo_vialidad": "CALLE",
  "nombre_vialidad": "CUBA",
  "numero_exterior": "1017",
  "numero_interior": "",
  "cp": "88290",
  "correo": "",
  "al": "",
  "RFC_ETIQUETA": "RAFA900621CVA",
  "NOMBRE_ETIQUETA": "ALEJANDRO RAMIREZ FLORES",
  "IDCIF_ETIQUETA": "15110155053"
}