{
  "D1": "10",
  "D2": "1",
  "D3": "16010903756_GAAA880507TR2",
  "rfc": "GAAA880507TR2",
  "curp": "GAAA880507MJCRMR05",
  "nombre": "ARCELIA YANETT",
  "apellido_paterno": "GARCIA",
  "apellido_materno": "AMADOR",
  "fecha_nacimiento": "07-05-1988",
  "fecha_inicio_operaciones": "15-12-2006",
  "situacion_contribuyente": "ACTIVO",
  "fecha_ultimo_cambio": "15-12-2006",
  "regimen": "Régimen de Sueldos y Salarios e Ingresos Asimilados a Salarios",
  "fecha_alta": "15-12-2006",
  "entidad": "JALISCO",
  "municipio": "SAN PEDRO TLAQUEPAQUE",
  "colonia": "ARTESANOS",
  "tipo_vialidad": "CALLE",
  "nombre_vialidad": "SIN NOMBRE",
  "numero_exterior": "205",
  "numero_interior": "",
  "cp": "45598",
  "correo": "",
  "al": "JALISCO 1",
  "RFC_ETIQUETA": "GAAA880507TR2",
  "NOMBRE_ETIQUETA": "ARCELIA YANETT GARCIA AMADOR",
  "IDCIF_ETIQUETA": "16010903756"
}