{
  "D1": "10",
  "D2": "1",
  "D3": "16020491965_SAMA7301088C0",
  "rfc": "SAMA7301088C0",
  "curp": "SAMA730108HNLNRN07",
  "nombre": "JOSE ANTONIO",
  "apellido_paterno": "SANCHEZ",
  "apellido_materno": "MERCADO",
  "fecha_nacimiento": "",
  "fecha_inicio_operaciones": "",
  "situacion_contribuyente": "SUSPENDIDO",
  "fecha_ultimo_cambio": "",
  "regimen": "",
  "fecha_alta": "",
  "entidad": "NUEVO LEON",
  "municipio": "EL CARMEN",
  "colonia": "OTRA NO ESPECIFICADA EN EL CATALOGO",
  "tipo_vialidad": "CALLE",
  "nombre_vialidad": "MESETA",
  "numero_exterior": "607",
  "numero_interior": "",
  "cp": "66550",
  "correo": "",
  "al": "",
  "RFC_ETIQUETA": "SAMA7301088C0",
  "NOMBRE_ETIQUETA": "JOSE ANTONIO SANCHEZ MERCADO",
  "IDCIF_ETIQUETA": "16020491965"
}