{
  "D1": "10",
  "D2": "1",
  "D3": "16030586338_GAHW820220LX3",
  "rfc": "GAHW820220LX3",
  "curp": "GAHW820220HOCRRL07",
  "nombre": "WILFRIDO",
  "apellido_paterno": "GARCIA",
  "apellido_materno": "HERNANDEZ",
  "fecha_nacimiento": "",
  "fecha_inicio_operaciones": "",
  "situacion_contribuyente": "ACTIVO",
  "fecha_ultimo_cambio": "",
  "regimen": "Régimen de las Personas Físicas con Actividades Empresariales y Profesionales",
  "fecha_alta": "",
  "entidad": "OAXACA",
  "municipio": "GUELATAO DE JUAREZ",
  "colonia": "CENTRO",
  "tipo_vialidad": "",
  "nombre_vialidad": "AV BENITO JUAREZ",
  "numero_exterior": "SN",
  "numero_interior": "",
  "cp": "68770",
  "correo": "",
  "al": "",
  "RFC_ETIQUETA": "GAHW820220LX3",
  "NOMBRE_ETIQUETA": "WILFRIDO GARCIA HERNANDEZ",
  "IDCIF_ETIQUETA": "16030586338"
}