{
  "D1": "10",
  "D2": "1",
  "D3": "16070443264_CUMM970918F61",
  "rfc": "CUMM970918F61",
  "curp": "CUMM970918HTSRRR01",
  "nombre": "MARCOS ALBERTO",
  "apellido_paterno": "CRUZ",
  "apellido_materno": "MARTINEZ",
  "fecha_nacimiento": "",
  "fecha_inicio_operaciones": "",
  "situacion_contribuyente": "ACTIVO",
  "fecha_ultimo_cambio": "",
  "regimen": "Régimen de Sueldos y Salarios e Ingresos Asimilados a Salarios",
  "fecha_alta": "",
  "entidad": "TAMAULIPAS",
  "municipio": "RIO BRAVO",
  "colonia": "LAS MARGARITAS",
  "tipo_vialidad": "CALLE",
  "nombre_vialidad": "GUANAJUATO",
  "numero_exterior": "166",
  "numero_interior": "",
  "cp": "88923",
  "correo": "",
  "al": "",
  "RFC_ETIQUETA": "CUMM970918F61",
  "NOMBRE_ETIQUETA": "MARCOS ALBERTO CRUZ MARTINEZ",
  "IDCIF_ETIQUETA": "16070443264"
}