{
  "D1": "10",
  "D2": "1",
  "D3": "16120501683_GONU910527SB5",
  "rfc": "GONU910527SB5",
  "curp": "GONU910527HMCMVR03",
  "nombre": "URIEL",
  "apellido_paterno": "GOMEZ",
  "apellido_materno": "NAVARRO",
  "fecha_nacimiento": "",
  "fecha_inicio_operaciones": "",
  "situacion_contribuyente": "ACTIVO",
  "fecha_ultimo_cambio": "",
  "regimen": "Régimen de Sueldos y Salarios e Ingresos Asimilados a Salarios",
  "fecha_alta": "",
  "entidad": "MEXICO",
  "municipio": "TENANGO DEL VALLE",
  "colonia": "OTRA NO ESPECIFICADA EN EL CATALOGO",
  "tipo_vialidad": "CALLE",
  "nombre_vialidad": "CUAYHTEMOC",
  "numero_exterior": "224",
  "numero_interior": "SN",
  "cp": "52330",
  "correo": "",
  "al": "",
  "RFC_ETIQUETA": "GONU910527SB5",
  "NOMBRE_ETIQUETA": "URIEL GOMEZ NAVARRO",
  "IDCIF_ETIQUETA": "16120501683"
}