{
  "D1": "10",
  "D2": "1",
  "D3": "16120174803_VAUJ870901M95",
  "rfc": "VAUJ870901M95",
  "curp": "VAUJ870901HMCRRS01",
  "nombre": "JASIEL CHRISTIAN",
  "apellido_paterno": "VARGAS",
  "apellido_materno": "URUEÑA",
  "fecha_nacimiento": "",
  "fecha_inicio_operaciones": "",
  "situacion_contribuyente": "ACTIVO",
  "fecha_ultimo_cambio": "",
  "regimen": "Régimen de las Actividades Empresariales con ingresos a través de Plataformas Tecnológicas.",
  "fecha_alta": "",
  "entidad": "MEXICO",
  "municipio": "NEZAHUALCOYOTL",
  "colonia": "CAMPESTRE GUADALUPANA",
  "tipo_vialidad": "CALLE",
  "nombre_vialidad": "CALLE 10",
  "numero_exterior": "56",
  "numero_interior": "",
  "cp": "57120",
  "correo": "",
  "al": "",
  "RFC_ETIQUETA": "VAUJ870901M95",
  "NOMBRE_ETIQUETA": "JASIEL CHRISTIAN VARGAS URUEÑA",
  "IDCIF_ETIQUETA": "16120174803"
}