{
  "D1": "10",
  "D2": "1",
  "D3": "16749172055_CACC9511105M0",
  "rfc": "CACC9511105M0",
  "curp": "CACC951110HDFSBR08",
  "nombre": "CRISTIAN ALBERTO",
  "apellido_paterno": "CASTILLO",
  "apellido_materno": "CABALLERO",
  "fecha_nacimiento": "10-11-1995",
  "fecha_inicio_operaciones": "21-04-2013",
  "situacion_contribuyente": "ACTIVO",
  "fecha_ultimo_cambio": "21-04-2013",
  "regimen": "Régimen de Sueldos y Salarios e Ingresos Asimilados a Salarios",
  "fecha_alta": "21-04-2013",
  "entidad": "DISTRITO FEDERAL",
  "municipio": "GUSTAVO A MADERO",
  "colonia": "",
  "tipo_vialidad": "CALLE",
  "nombre_vialidad": "SIN NOMBRE",
  "numero_exterior": "580",
  "numero_interior": "",
  "cp": "",
  "correo": "",
  "al": "DISTRITO FEDERAL 1",
  "RFC_ETIQUETA": "CACC9511105M0",
  "NOMBRE_ETIQUETA": "CRISTIAN ALBERTO CASTILLO CABALLERO",
  "IDCIF_ETIQUETA": "16749172055"
}