{
  "D1": "10",
  "D2": "1",
  "D3": "17013087304_MOVG010731FQA",
  "rfc": "MOVG010731FQA",
  "curp": "MOVG010731MGTRRDA9",
  "nombre": "MARIA GUADALUPE",
  "apellido_paterno": "MORENO",
  "apellido_materno": "VARGAS",
  "fecha_nacimiento": "31-07-2001",
  "fecha_inicio_operaciones": "15-06-2019",
  "situacion_contribuyente": "ACTIVO",
  "fecha_ultimo_cambio": "15-06-2019",
  "regimen": "Régimen de Sueldos y Salarios e Ingresos Asimilados a Salarios",
  "fecha_alta": "15-06-2019",
  "entidad": "GUANAJUATO",
  "municipio": "LEÓN",
  "colonia": "LA CAPILLA DE ALFARO",
  "tipo_vialidad": "CALLE",
  "nombre_vialidad": "SIN NOMBRE",
  "numero_exterior": "816",
  "numero_interior": "",
  "cp": "37233",
  "correo": "",
  "al": "GUANAJUATO 1",
  "RFC_ETIQUETA": "MOVG010731FQA",
  "NOMBRE_ETIQUETA": "MARIA GUADALUPE MORENO VARGAS",
  "IDCIF_ETIQUETA": "17013087304"
}