{
  "D1": "10",
  "D2": "1",
  "D3": "17070491221_CACR710909L79",
  "rfc": "CACR710909L79",
  "curp": "CACR710909HPLBRC04",
  "nombre": "RICARDO",
  "apellido_paterno": "CABRERA",
  "apellido_materno": "CRUZ",
  "fecha_nacimiento": "",
  "fecha_inicio_operaciones": "",
  "situacion_contribuyente": "REACTIVADO",
  "fecha_ultimo_cambio": "",
  "regimen": "Régimen Simplificado de Confianza",
  "fecha_alta": "",
  "entidad": "PUEBLA",
  "municipio": "PUEBLA",
  "colonia": "HISTORIADORES",
  "tipo_vialidad": "ANDADOR",
  "nombre_vialidad": "E. CORDERO Y TORRES",
  "numero_exterior": "125",
  "numero_interior": "",
  "cp": "72365",
  "correo": "",
  "al": "",
  "RFC_ETIQUETA": "CACR710909L79",
  "NOMBRE_ETIQUETA": "RICARDO CABRERA CRUZ",
  "IDCIF_ETIQUETA": "17070491221"
}