{
  "D1": "10",
  "D2": "1",
  "D3": "17404143977_CAAJ6404097V7",
  "rfc": "CAAJ6404097V7",
  "curp": "CAAJ640409MHGNRN01",
  "nombre": "JUANA",
  "apellido_paterno": "CANALES",
  "apellido_materno": "ARTEAGA",
  "fecha_nacimiento": "09-04-1964",
  "fecha_inicio_operaciones": "19-06-1982",
  "situacion_contribuyente": "ACTIVO",
  "fecha_ultimo_cambio": "19-06-1982",
  "regimen": "Régimen Simplificado de Confianza",
  "fecha_alta": "19-06-1982",
  "entidad": "HIDALGO",
  "municipio": "TULANCINGO DE BRAVO",
  "colonia": "ACOCUL GUADALUPE",
  "tipo_vialidad": "CALLE",
  "nombre_vialidad": "SIN NOMBRE",
  "numero_exterior": "365",
  "numero_interior": "",
  "cp": "43707",
  "correo": "",
  "al": "HIDALGO 1",
  "RFC_ETIQUETA": "CAAJ6404097V7",
  "NOMBRE_ETIQUETA": "JUANA CANALES ARTEAGA",
  "IDCIF_ETIQUETA": "17404143977"
}