{
  "D1": "10",
  "D2": "1",
  "D3": "17820488783_AULA970303230",
  "rfc": "AULA970303230",
  "curp": "AULA970303HSPGRN04",
  "nombre": "JOSE ANDRES",
  "apellido_paterno": "AGUILAR",
  "apellido_materno": "LOREDO",
  "fecha_nacimiento": "03-03-1997",
  "fecha_inicio_operaciones": "02-03-2015",
  "situacion_contribuyente": "ACTIVO",
  "fecha_ultimo_cambio": "02-03-2015",
  "regimen": "Régimen de Sueldos y Salarios e Ingresos Asimilados a Salarios",
  "fecha_alta": "02-03-2015",
  "entidad": "SAN LUIS POTOSÍ",
  "municipio": "SAN LUIS POTOSÍ",
  "colonia": "NARANJOS",
  "tipo_vialidad": "CALLE",
  "nombre_vialidad": "SIN NOMBRE",
  "numero_exterior": "76",
  "numero_interior": "",
  "cp": "78146",
  "correo": "",
  "al": "SAN LUIS POTOSÍ 1",
  "RFC_ETIQUETA": "AULA970303230",
  "NOMBRE_ETIQUETA": "JOSE ANDRES AGUILAR LOREDO",
  "IDCIF_ETIQUETA": "17820488783"
}