{
  "D1": "10",
  "D2": "1",
  "D3": "18040009474_LOAF000228PC1",
  "rfc": "LOAF000228PC1",
  "curp": "LOAF000228HSRPYLA8",
  "nombre": "FLAVIO ENRIQUE",
  "apellido_paterno": "LOPEZ",
  "apellido_materno": "AYALA",
  "fecha_nacimiento": "",
  "fecha_inicio_operaciones": "",
  "situacion_contribuyente": "ACTIVO",
  "fecha_ultimo_cambio": "",
  "regimen": "Régimen de Sueldos y Salarios e Ingresos Asimilados a Salarios",
  "fecha_alta": "",
  "entidad": "SONORA",
  "municipio": "NOGALES",
  "colonia": "LAS BELLOTAS",
  "tipo_vialidad": "CALLE",
  "nombre_vialidad": "HIGUERAS",
  "numero_exterior": "8",
  "numero_interior": "SIN NUMERO",
  "cp": "84094",
  "correo": "",
  "al": "",
  "RFC_ETIQUETA": "LOAF000228PC1",
  "NOMBRE_ETIQUETA": "FLAVIO ENRIQUE LOPEZ AYALA",
  "IDCIF_ETIQUETA": "18040009474"
}