{
  "D1": "10",
  "D2": "1",
  "D3": "18080117631_TICL010719J8A",
  "rfc": "TICL010719J8A",
  "curp": "TICL010719HCHRRSA5",
  "nombre": "LUIS ALONSO",
  "apellido_paterno": "TRILLO",
  "apellido_materno": "CORDOVA",
  "fecha_nacimiento": "",
  "fecha_inicio_operaciones": "",
  "situacion_contribuyente": "SUSPENDIDO",
  "fecha_ultimo_cambio": "",
  "regimen": "",
  "fecha_alta": "",
  "entidad": "CHIHUAHUA",
  "municipio": "CHIHUAHUA",
  "colonia": "LOS OLIVOS",
  "tipo_vialidad": "CALLE",
  "nombre_vialidad": "OLIVAR DE ARAGON",
  "numero_exterior": "682",
  "numero_interior": "",
  "cp": "31144",
  "correo": "",
  "al": "",
  "RFC_ETIQUETA": "TICL010719J8A",
  "NOMBRE_ETIQUETA": "LUIS ALONSO TRILLO CORDOVA",
  "IDCIF_ETIQUETA": "18080117631"
}