{
  "D1": "10",
  "D2": "1",
  "D3": "18129854662_PEPM610713QS4",
  "rfc": "PEPM610713QS4",
  "curp": "PEPM610713MHGRRR00",
  "nombre": "MARTHA",
  "apellido_paterno": "PEREZ",
  "apellido_materno": "PEREZ",
  "fecha_nacimiento": "13-07-1961",
  "fecha_inicio_operaciones": "23-09-1979",
  "situacion_contribuyente": "ACTIVO",
  "fecha_ultimo_cambio": "23-09-1979",
  "regimen": "Régimen de Sueldos y Salarios e Ingresos Asimilados a Salarios",
  "fecha_alta": "23-09-1979",
  "entidad": "HIDALGO",
  "municipio": "MIXQUIAHUALA DE JUÁREZ",
  "colonia": "CAÑADA",
  "tipo_vialidad": "CALLE",
  "nombre_vialidad": "SIN NOMBRE",
  "numero_exterior": "634",
  "numero_interior": "",
  "cp": "42701",
  "correo": "",
  "al": "HIDALGO 1",
  "RFC_ETIQUETA": "PEPM610713QS4",
  "NOMBRE_ETIQUETA": "MARTHA PEREZ PEREZ",
  "IDCIF_ETIQUETA": "18129854662"
}