{
  "D1": "10",
  "D2": "1",
  "D3": "18120013644_RARB9201147E3",
  "rfc": "RARB9201147E3",
  "curp": "RARB920114MPLMJN05",
  "nombre": "BIANCA CELESTE",
  "apellido_paterno": "RAMIREZ",
  "apellido_materno": "ROJAS",
  "fecha_nacimiento": "",
  "fecha_inicio_operaciones": "",
  "situacion_contribuyente": "ACTIVO",
  "fecha_ultimo_cambio": "",
  "regimen": "Régimen de Sueldos y Salarios e Ingresos Asimilados a Salarios",
  "fecha_alta": "",
  "entidad": "CIUDAD DE MEXICO",
  "municipio": "ALVARO OBREGON",
  "colonia": "LAS AGUILAS",
  "tipo_vialidad": "",
  "nombre_vialidad": "BOULEVARD ADOLFO LOPEZ MATEOS",
  "numero_exterior": "2273 ANTES 515",
  "numero_interior": "",
  "cp": "01710",
  "correo": "",
  "al": "",
  "RFC_ETIQUETA": "RARB9201147E3",
  "NOMBRE_ETIQUETA": "BIANCA CELESTE RAMIREZ ROJAS",
  "IDCIF_ETIQUETA": "18120013644"
}