{
  "D1": "10",
  "D2": "1",
  "D3": "19518307127_LOLJ640209U43",
  "rfc": "LOLJ640209U43",
  "curp": "LOLJ640209HBCPPQ15",
  "nombre": "JOAQUIN",
  "apellido_paterno": "LOPEZ",
  "apellido_materno": "LOPEZ",
  "fecha_nacimiento": "09-02-1964",
  "fecha_inicio_operaciones": "28-07-1982",
  "situacion_contribuyente": "ACTIVO",
  "fecha_ultimo_cambio": "28-07-1982",
  "regimen": "Régimen de Sueldos y Salarios e Ingresos Asimilados a Salarios",
  "fecha_alta": "28-07-1982",
  "entidad": "BAJA CALIFORNIA",
  "municipio": "MEXICALI",
  "colonia": "NICOLÁS BRAVO",
  "tipo_vialidad": "CALLE",
  "nombre_vialidad": "SIN NOMBRE",
  "numero_exterior": "380",
  "numero_interior": "",
  "cp": "21720",
  "correo": "",
  "al": "BAJA CALIFORNIA 1",
  "RFC_ETIQUETA": "LOLJ640209U43",
  "NOMBRE_ETIQUETA": "JOAQUIN LOPEZ LOPEZ",
  "IDCIF_ETIQUETA": "19518307127"
}