{
  "D1": "10",
  "D2": "1",
  "D3": "19951586987_CAFJ020617L61",
  "rfc": "CAFJ020617L61",
  "curp": "CAFJ020617HJCSLNA5",
  "nombre": "JONATHAN",
  "apellido_paterno": "CASTELLANOS",
  "apellido_materno": "FELIX",
  "fecha_nacimiento": "17-06-2002",
  "fecha_inicio_operaciones": "29-01-2020",
  "situacion_contribuyente": "ACTIVO",
  "fecha_ultimo_cambio": "29-01-2020",
  "regimen": "Sin obligaciones fiscales",
  "fecha_alta": "29-01-2020",
  "entidad": "JALISCO",
  "municipio": "TONALÁ",
  "colonia": "ARCOS DE ZALATITAN",
  "tipo_vialidad": "CALLE",
  "nombre_vialidad": "SIN NOMBRE",
  "numero_exterior": "755",
  "numero_interior": "",
  "cp": "45406",
  "correo": "",
  "al": "JALISCO 1",
  "RFC_ETIQUETA": "CAFJ020617L61",
  "NOMBRE_ETIQUETA": "JONATHAN CASTELLANOS FELIX",
  "IDCIF_ETIQUETA": "19951586987"
}