{
  "D1": "10",
  "D2": "1",
  "D3": "20020195509_VAOM020110HC0",
  "rfc": "VAOM020110HC0",
  "curp": "VAOM020110MDFZLRA2",
  "nombre": "MARY GRACIELA",
  "apellido_paterno": "VAZQUEZ",
  "apellido_materno": "OLVERA",
  "fecha_nacimiento": "",
  "fecha_inicio_operaciones": "",
  "situacion_contribuyente": "ACTIVO",
  "fecha_ultimo_cambio": "",
  "regimen": "Régimen de Ingresos por Dividendos (socios y accionistas)",
  "fecha_alta": "",
  "entidad": "CIUDAD DE MEXICO",
  "municipio": "GUSTAVO A MADERO",
  "colonia": "TICOMAN",
  "tipo_vialidad": "CALZADA  (CALZ.)",
  "nombre_vialidad": "AVENIDA TICOMAN",
  "numero_exterior": "2248",
  "numero_interior": "4",
  "cp": "07330",
  "correo": "",
  "al": "",
  "RFC_ETIQUETA": "VAOM020110HC0",
  "NOMBRE_ETIQUETA": "MARY GRACIELA VAZQUEZ OLVERA",
  "IDCIF_ETIQUETA": "20020195509"
}