{
  "D1": "10",
  "D2": "1",
  "D3": "20032614723_MAFP8307319N6",
  "rfc": "MAFP8307319N6",
  "curp": "MAFP830731HZSRHT07",
  "nombre": "PETER",
  "apellido_paterno": "MARTENS",
  "apellido_materno": "FEHR",
  "fecha_nacimiento": "31-07-1983",
  "fecha_inicio_operaciones": "07-09-2001",
  "situacion_contribuyente": "ACTIVO",
  "fecha_ultimo_cambio": "07-09-2001",
  "regimen": "Sin obligaciones fiscales",
  "fecha_alta": "07-09-2001",
  "entidad": "CAMPECHE",
  "municipio": "HOPELCHÉN",
  "colonia": "CAMPO DE AVIACIÓN",
  "tipo_vialidad": "CALLE",
  "nombre_vialidad": "SIN NOMBRE",
  "numero_exterior": "831",
  "numero_interior": "",
  "cp": "24600",
  "correo": "",
  "al": "CAMPECHE 1",
  "RFC_ETIQUETA": "MAFP8307319N6",
  "NOMBRE_ETIQUETA": "PETER MARTENS FEHR",
  "IDCIF_ETIQUETA": "20032614723"
}