{
  "D1": "10",
  "D2": "1",
  "D3": "20090012648_NAGC020815BN8",
  "rfc": "NAGC020815BN8",
  "curp": "NAGC020815MJCVMNA3",
  "nombre": "CINTHYA ARACELI",
  "apellido_paterno": "NAVARRO",
  "apellido_materno": "GOMEZ",
  "fecha_nacimiento": "",
  "fecha_inicio_operaciones": "",
  "situacion_contribuyente": "ACTIVO",
  "fecha_ultimo_cambio": "",
  "regimen": "Sin obligaciones fiscales",
  "fecha_alta": "",
  "entidad": "JALISCO",
  "municipio": "TALA",
  "colonia": "",
  "tipo_vialidad": "",
  "nombre_vialidad": "FLORES MAGON",
  "numero_exterior": "100",
  "numero_interior": "100",
  "cp": "45300",
  "correo": "",
  "al": "",
  "RFC_ETIQUETA": "NAGC020815BN8",
  "NOMBRE_ETIQUETA": "CINTHYA ARACELI NAVARRO GOMEZ",
  "IDCIF_ETIQUETA": "20090012648"
}