{
  "D1": "10",
  "D2": "1",
  "D3": "20090024045_DISH990804KY0",
  "rfc": "DISH990804KY0",
  "curp": "DISH990804HCSSBR07",
  "nombre": "HORACIO",
  "apellido_paterno": "DIAS",
  "apellido_materno": "SEBADUA",
  "fecha_nacimiento": "",
  "fecha_inicio_operaciones": "",
  "situacion_contribuyente": "ACTIVO",
  "fecha_ultimo_cambio": "",
  "regimen": "Sin obligaciones fiscales",
  "fecha_alta": "",
  "entidad": "CHIAPAS",
  "municipio": "VILLAFLORES",
  "colonia": "OTRA NO ESPECIFICADA EN EL CATALOGO",
  "tipo_vialidad": "CALLE",
  "nombre_vialidad": "CALZADA",
  "numero_exterior": "SN",
  "numero_interior": "SN",
  "cp": "30495",
  "correo": "",
  "al": "",
  "RFC_ETIQUETA": "DISH990804KY0",
  "NOMBRE_ETIQUETA": "HORACIO DIAS SEBADUA",
  "IDCIF_ETIQUETA": "20090024045"
}