{
  "D1": "10",
  "D2": "1",
  "D3": "20321679669_EOGM690613AU6",
  "rfc": "EOGM690613AU6",
  "curp": "EOGM690613HTSSNR02",
  "nombre": "MARCO ANTONIO",
  "apellido_paterno": "ESCOBEDO",
  "apellido_materno": "GONZALEZ",
  "fecha_nacimiento": "13-06-1969",
  "fecha_inicio_operaciones": "14-07-1987",
  "situacion_contribuyente": "ACTIVO",
  "fecha_ultimo_cambio": "14-07-1987",
  "regimen": "Régimen de Sueldos y Salarios e Ingresos Asimilados a Salarios",
  "fecha_alta": "14-07-1987",
  "entidad": "TAMAULIPAS",
  "municipio": "REYNOSA",
  "colonia": "LAREDO",
  "tipo_vialidad": "CALLE",
  "nombre_vialidad": "SIN NOMBRE",
  "numero_exterior": "463",
  "numero_interior": "",
  "cp": "88708",
  "correo": "",
  "al": "TAMAULIPAS 1",
  "RFC_ETIQUETA": "EOGM690613AU6",
  "NOMBRE_ETIQUETA": "MARCO ANTONIO ESCOBEDO GONZALEZ",
  "IDCIF_ETIQUETA": "20321679669"
}