{
  "D1": "10",
  "D2": "1",
  "D3": "20840838279_EARM0705168BA",
  "rfc": "EARM0705168BA",
  "curp": "EARM070516HGTSCRA5",
  "nombre": "MARTIN ADRIAN",
  "apellido_paterno": "ESTRADA",
  "apellido_materno": "ROCHA",
  "fecha_nacimiento": "16-05-2007",
  "fecha_inicio_operaciones": "30-12-2025",
  "situacion_contribuyente": "ACTIVO",
  "fecha_ultimo_cambio": "30-12-2025",
  "regimen": "Régimen de Sueldos y Salarios e Ingresos Asimilados a Salarios",
  "fecha_alta": "30-12-2025",
  "entidad": "GUANAJUATO",
  "municipio": "LEÓN",
  "colonia": "SAN RAFAEL",
  "tipo_vialidad": "CALLE",
  "nombre_vialidad": "SIN NOMBRE",
  "numero_exterior": "783",
  "numero_interior": "",
  "cp": "37380",
  "correo": "",
  "al": "GUANAJUATO 1",
  "RFC_ETIQUETA": "EARM0705168BA",
  "NOMBRE_ETIQUETA": "MARTIN ADRIAN ESTRADA ROCHA",
  "IDCIF_ETIQUETA": "20840838279"
}