{
  "D1": "10",
  "D2": "1",
  "D3": "21020304140_GATD981124732",
  "rfc": "GATD981124732",
  "curp": "GATD981124MOCRLL08",
  "nombre": "DULCE AILED",
  "apellido_paterno": "GARCIA",
  "apellido_materno": "TOLEDO",
  "fecha_nacimiento": "",
  "fecha_inicio_operaciones": "",
  "situacion_contribuyente": "ACTIVO",
  "fecha_ultimo_cambio": "",
  "regimen": "Sin obligaciones fiscales",
  "fecha_alta": "",
  "entidad": "OAXACA",
  "municipio": "SANTO DOMINGO TEHUANTEPEC",
  "colonia": "BENITO JUAREZ",
  "tipo_vialidad": "",
  "nombre_vialidad": "CAMPECHE",
  "numero_exterior": "42",
  "numero_interior": "",
  "cp": "70760",
  "correo": "",
  "al": "",
  "RFC_ETIQUETA": "GATD981124732",
  "NOMBRE_ETIQUETA": "DULCE AILED GARCIA TOLEDO",
  "IDCIF_ETIQUETA": "21020304140"
}