{
  "D1": "10",
  "D2": "1",
  "D3": "21070068175_EERE0303054R7",
  "rfc": "EERE0303054R7",
  "curp": "EERE030305MMCSYDA9",
  "nombre": "EDNA BERENICE",
  "apellido_paterno": "ESTEVEZ",
  "apellido_materno": "RAYMUNDO",
  "fecha_nacimiento": "",
  "fecha_inicio_operaciones": "",
  "situacion_contribuyente": "ACTIVO",
  "fecha_ultimo_cambio": "",
  "regimen": "Sin obligaciones fiscales",
  "fecha_alta": "",
  "entidad": "MEXICO",
  "municipio": "VALLE DE CHALCO SOLIDARIDAD",
  "colonia": "GEOVILLAS LA ASUNCION",
  "tipo_vialidad": "ANDADOR",
  "nombre_vialidad": "A",
  "numero_exterior": "5",
  "numero_interior": "551",
  "cp": "56618",
  "correo": "",
  "al": "",
  "RFC_ETIQUETA": "EERE0303054R7",
  "NOMBRE_ETIQUETA": "EDNA BERENICE ESTEVEZ RAYMUNDO",
  "IDCIF_ETIQUETA": "21070068175"
}