{
  "D1": "10",
  "D2": "1",
  "D3": "21798024992_CAEK000808F39",
  "rfc": "CAEK000808F39",
  "curp": "CAEK000808MCHLSRA3",
  "nombre": "KARLA ALEJANDRA",
  "apellido_paterno": "CLARO",
  "apellido_materno": "ESQUIVEL",
  "fecha_nacimiento": "08-08-2000",
  "fecha_inicio_operaciones": "21-06-2018",
  "situacion_contribuyente": "ACTIVO",
  "fecha_ultimo_cambio": "21-06-2018",
  "regimen": "Régimen de Sueldos y Salarios e Ingresos Asimilados a Salarios",
  "fecha_alta": "21-06-2018",
  "entidad": "CHIHUAHUA",
  "municipio": "DELICIAS",
  "colonia": "EL REFUGIO",
  "tipo_vialidad": "CALLE",
  "nombre_vialidad": "SIN NOMBRE",
  "numero_exterior": "392",
  "numero_interior": "",
  "cp": "33087",
  "correo": "",
  "al": "CHIHUAHUA 1",
  "RFC_ETIQUETA": "CAEK000808F39",
  "NOMBRE_ETIQUETA": "KARLA ALEJANDRA CLARO ESQUIVEL",
  "IDCIF_ETIQUETA": "21798024992"
}