{
  "D1": "10",
  "D2": "1",
  "D3": "22030039810_QUGA950613780",
  "rfc": "QUGA950613780",
  "curp": "QUGA950613MHGNRM03",
  "nombre": "AMAYRANI",
  "apellido_paterno": "QUINTOS",
  "apellido_materno": "GARCIA",
  "fecha_nacimiento": "",
  "fecha_inicio_operaciones": "",
  "situacion_contribuyente": "ACTIVO",
  "fecha_ultimo_cambio": "",
  "regimen": "Régimen de Sueldos y Salarios e Ingresos Asimilados a Salarios",
  "fecha_alta": "",
  "entidad": "HIDALGO",
  "municipio": "EMILIANO ZAPATA",
  "colonia": "EMILIANO ZAPATA CENTRO",
  "tipo_vialidad": "CALLE",
  "nombre_vialidad": "C CORREGIDORA",
  "numero_exterior": "16",
  "numero_interior": "1",
  "cp": "43960",
  "correo": "",
  "al": "",
  "RFC_ETIQUETA": "QUGA950613780",
  "NOMBRE_ETIQUETA": "AMAYRANI QUINTOS GARCIA",
  "IDCIF_ETIQUETA": "22030039810"
}