{
  "D1": "10",
  "D2": "1",
  "D3": "22060575290_DIVA860408B18",
  "rfc": "DIVA860408B18",
  "curp": "DIVA860408HDFZLR07",
  "nombre": "ARTURO ALBERTO",
  "apellido_paterno": "DIAZ",
  "apellido_materno": "VALDES",
  "fecha_nacimiento": "",
  "fecha_inicio_operaciones": "",
  "situacion_contribuyente": "ACTIVO",
  "fecha_ultimo_cambio": "",
  "regimen": "Régimen de Sueldos y Salarios e Ingresos Asimilados a Salarios",
  "fecha_alta": "",
  "entidad": "CIUDAD DE MEXICO",
  "municipio": "MIGUEL HIDALGO",
  "colonia": "CHAPULTEPEC MORALES",
  "tipo_vialidad": "",
  "nombre_vialidad": "MONTE ELBRUZ",
  "numero_exterior": "132",
  "numero_interior": "10",
  "cp": "11570",
  "correo": "",
  "al": "",
  "RFC_ETIQUETA": "DIVA860408B18",
  "NOMBRE_ETIQUETA": "ARTURO ALBERTO DIAZ VALDES",
  "IDCIF_ETIQUETA": "22060575290"
}