{
  "D1": "10",
  "D2": "1",
  "D3": "22060749914_AUER891102ST6",
  "rfc": "AUER891102ST6",
  "curp": "AUER891102HQRGSB07",
  "nombre": "RUBEN NEFTALI",
  "apellido_paterno": "AGUIRRE",
  "apellido_materno": "ESCALANTE",
  "fecha_nacimiento": "",
  "fecha_inicio_operaciones": "",
  "situacion_contribuyente": "ACTIVO",
  "fecha_ultimo_cambio": "",
  "regimen": "Régimen de Sueldos y Salarios e Ingresos Asimilados a Salarios",
  "fecha_alta": "",
  "entidad": "QUINTANA ROO",
  "municipio": "BENITO JUAREZ",
  "colonia": "REGION 239 PTO MORELOS",
  "tipo_vialidad": "",
  "nombre_vialidad": "SM 12 LT 16 PUERTO MORELOS BENITO JUAREZ QUINTANA",
  "numero_exterior": "SR",
  "numero_interior": "",
  "cp": "77580",
  "correo": "",
  "al": "",
  "RFC_ETIQUETA": "AUER891102ST6",
  "NOMBRE_ETIQUETA": "RUBEN NEFTALI AGUIRRE ESCALANTE",
  "IDCIF_ETIQUETA": "22060749914"
}