{
  "D1": "10",
  "D2": "1",
  "D3": "22061595863_CORE840522B94",
  "rfc": "CORE840522B94",
  "curp": "CORE840522MTLNCL06",
  "nombre": "MARIA ELIZABETH",
  "apellido_paterno": "CONTRERAS",
  "apellido_materno": "ROCHA",
  "fecha_nacimiento": "",
  "fecha_inicio_operaciones": "",
  "situacion_contribuyente": "ACTIVO",
  "fecha_ultimo_cambio": "",
  "regimen": "Régimen de Sueldos y Salarios e Ingresos Asimilados a Salarios",
  "fecha_alta": "",
  "entidad": "PUEBLA",
  "municipio": "PUEBLA",
  "colonia": "PUEBLA CENTRO",
  "tipo_vialidad": "",
  "nombre_vialidad": "2 PONIENTE",
  "numero_exterior": "101",
  "numero_interior": "201",
  "cp": "72000",
  "correo": "",
  "al": "",
  "RFC_ETIQUETA": "CORE840522B94",
  "NOMBRE_ETIQUETA": "MARIA ELIZABETH CONTRERAS ROCHA",
  "IDCIF_ETIQUETA": "22061595863"
}