{
  "D1": "10",
  "D2": "1",
  "D3": "22070174157_AACK031031EC6",
  "rfc": "AACK031031EC6",
  "curp": "AACK031031MVZNLTA3",
  "nombre": "KATHERINE PAOLA",
  "apellido_paterno": "ANDRADE",
  "apellido_materno": "CULEBRO",
  "fecha_nacimiento": "",
  "fecha_inicio_operaciones": "",
  "situacion_contribuyente": "ACTIVO",
  "fecha_ultimo_cambio": "",
  "regimen": "Sin obligaciones fiscales",
  "fecha_alta": "",
  "entidad": "VERACRUZ DE IGNACIO DE LA LLAVE",
  "municipio": "TUXPAN",
  "colonia": "UNIVERSITARIA",
  "tipo_vialidad": "CALLE",
  "nombre_vialidad": "CIRCUITO MONACO",
  "numero_exterior": "18",
  "numero_interior": "SIN NUMERO",
  "cp": "92895",
  "correo": "",
  "al": "",
  "RFC_ETIQUETA": "AACK031031EC6",
  "NOMBRE_ETIQUETA": "KATHERINE PAOLA ANDRADE CULEBRO",
  "IDCIF_ETIQUETA": "22070174157"
}