{
  "D1": "10",
  "D2": "1",
  "D3": "22110322183_DISL980601GX6",
  "rfc": "DISL980601GX6",
  "curp": "DISL980601MBCZLL04",
  "nombre": "LILIANA",
  "apellido_paterno": "DIAZ",
  "apellido_materno": "SALGADO",
  "fecha_nacimiento": "",
  "fecha_inicio_operaciones": "",
  "situacion_contribuyente": "ACTIVO",
  "fecha_ultimo_cambio": "",
  "regimen": "Régimen de Sueldos y Salarios e Ingresos Asimilados a Salarios",
  "fecha_alta": "",
  "entidad": "BAJA CALIFORNIA",
  "municipio": "TIJUANA",
  "colonia": "CAMINO VERDE (CAÑADA VERDE)",
  "tipo_vialidad": "ANDADOR",
  "nombre_vialidad": "TABASCO",
  "numero_exterior": "13323",
  "numero_interior": "SIN NUMERO",
  "cp": "22190",
  "correo": "",
  "al": "",
  "RFC_ETIQUETA": "DISL980601GX6",
  "NOMBRE_ETIQUETA": "LILIANA DIAZ SALGADO",
  "IDCIF_ETIQUETA": "22110322183"
}