{
  "D1": "10",
  "D2": "1",
  "D3": "22255272033_GUVS970527LP9",
  "rfc": "GUVS970527LP9",
  "curp": "GUVS970527HJCTCM08",
  "nombre": "SIMON",
  "apellido_paterno": "GUTIERREZ",
  "apellido_materno": "VICTORIANO",
  "fecha_nacimiento": "27-05-1997",
  "fecha_inicio_operaciones": "14-02-2015",
  "situacion_contribuyente": "ACTIVO",
  "fecha_ultimo_cambio": "14-02-2015",
  "regimen": "Sin obligaciones fiscales",
  "fecha_alta": "14-02-2015",
  "entidad": "COLIMA",
  "municipio": "TECOMÁN",
  "colonia": "ARTURO NORIEGA PIZANO",
  "tipo_vialidad": "CALLE",
  "nombre_vialidad": "SIN NOMBRE",
  "numero_exterior": "2",
  "numero_interior": "",
  "cp": "28900",
  "correo": "",
  "al": "COLIMA 1",
  "RFC_ETIQUETA": "GUVS970527LP9",
  "NOMBRE_ETIQUETA": "SIMON GUTIERREZ VICTORIANO",
  "IDCIF_ETIQUETA": "22255272033"
}