{
  "D1": "10",
  "D2": "1",
  "D3": "22284494961_MAAV7610133A1",
  "rfc": "MAAV7610133A1",
  "curp": "MAAV761013MJCGGR00",
  "nombre": "VERONICA",
  "apellido_paterno": "MAGALLANES",
  "apellido_materno": "AGUILAR",
  "fecha_nacimiento": "13-10-1976",
  "fecha_inicio_operaciones": "13-07-1994",
  "situacion_contribuyente": "ACTIVO",
  "fecha_ultimo_cambio": "13-07-1994",
  "regimen": "Régimen de Sueldos y Salarios e Ingresos Asimilados a Salarios",
  "fecha_alta": "13-07-1994",
  "entidad": "JALISCO",
  "municipio": "TOMATLÁN",
  "colonia": "EL OCOTILLO",
  "tipo_vialidad": "CALLE",
  "nombre_vialidad": "SIN NOMBRE",
  "numero_exterior": "872",
  "numero_interior": "",
  "cp": "48473",
  "correo": "",
  "al": "JALISCO 1",
  "RFC_ETIQUETA": "MAAV7610133A1",
  "NOMBRE_ETIQUETA": "VERONICA MAGALLANES AGUILAR",
  "IDCIF_ETIQUETA": "22284494961"
}