{
  "D1": "10",
  "D2": "1",
  "D3": "22742460499_ROOF920223QB8",
  "rfc": "ROOF920223QB8",
  "curp": "ROOF920223MZSSRR02",
  "nombre": "MARIA FERNANDA",
  "apellido_paterno": "ROSAS",
  "apellido_materno": "ORTIZ",
  "fecha_nacimiento": "23-02-1992",
  "fecha_inicio_operaciones": "11-04-2010",
  "situacion_contribuyente": "ACTIVO",
  "fecha_ultimo_cambio": "11-04-2010",
  "regimen": "Régimen de Sueldos y Salarios e Ingresos Asimilados a Salarios",
  "fecha_alta": "11-04-2010",
  "entidad": "ZACATECAS",
  "municipio": "GUADALUPE",
  "colonia": "CAMPESTRE SAN JOSÉ",
  "tipo_vialidad": "CALLE",
  "nombre_vialidad": "SIN NOMBRE",
  "numero_exterior": "385",
  "numero_interior": "",
  "cp": "98606",
  "correo": "",
  "al": "ZACATECAS 1",
  "RFC_ETIQUETA": "ROOF920223QB8",
  "NOMBRE_ETIQUETA": "MARIA FERNANDA ROSAS ORTIZ",
  "IDCIF_ETIQUETA": "22742460499"
}