{
  "D1": "10",
  "D2": "1",
  "D3": "23030136643_GARJ030803BP6",
  "rfc": "GARJ030803BP6",
  "curp": "GARJ030803MMCRYNA4",
  "nombre": "JENNIFER PAOLA",
  "apellido_paterno": "GARCIA",
  "apellido_materno": "REYES",
  "fecha_nacimiento": "",
  "fecha_inicio_operaciones": "",
  "situacion_contribuyente": "ACTIVO",
  "fecha_ultimo_cambio": "",
  "regimen": "Régimen de Sueldos y Salarios e Ingresos Asimilados a Salarios",
  "fecha_alta": "",
  "entidad": "MEXICO",
  "municipio": "CUAUTITLAN IZCALLI",
  "colonia": "COFRADIA SAN MIGUEL IV",
  "tipo_vialidad": "CALLE",
  "nombre_vialidad": "CAMINO DE LAS LOMAS",
  "numero_exterior": "MANZANA 17 LOTE 11 B",
  "numero_interior": "3 B",
  "cp": "54715",
  "correo": "",
  "al": "",
  "RFC_ETIQUETA": "GARJ030803BP6",
  "NOMBRE_ETIQUETA": "JENNIFER PAOLA GARCIA REYES",
  "IDCIF_ETIQUETA": "23030136643"
}