{
  "D1": "10",
  "D2": "1",
  "D3": "23060377149_BAHK040127TY5",
  "rfc": "BAHK040127TY5",
  "curp": "BAHK040127MCLRRRA2",
  "nombre": "KAREN JAKELIN",
  "apellido_paterno": "BARRON",
  "apellido_materno": "HERNANDEZ",
  "fecha_nacimiento": "",
  "fecha_inicio_operaciones": "",
  "situacion_contribuyente": "ACTIVO",
  "fecha_ultimo_cambio": "",
  "regimen": "Régimen de Sueldos y Salarios e Ingresos Asimilados a Salarios",
  "fecha_alta": "",
  "entidad": "DURANGO",
  "municipio": "LERDO",
  "colonia": "OTRA NO ESPECIFICADA EN EL CATALOGO",
  "tipo_vialidad": "AVENIDA  (AV.)",
  "nombre_vialidad": "BENITO JUAREZ",
  "numero_exterior": "SN",
  "numero_interior": "",
  "cp": "35188",
  "correo": "",
  "al": "",
  "RFC_ETIQUETA": "BAHK040127TY5",
  "NOMBRE_ETIQUETA": "KAREN JAKELIN BARRON HERNANDEZ",
  "IDCIF_ETIQUETA": "23060377149"
}