{
  "D1": "10",
  "D2": "1",
  "D3": "23142054702_GOGR890103AX8",
  "rfc": "GOGR890103AX8",
  "curp": "GOGR890103HPLMMF07",
  "nombre": "RAFAEL",
  "apellido_paterno": "GOMEZ",
  "apellido_materno": "GOMEZ",
  "fecha_nacimiento": "03-01-1989",
  "fecha_inicio_operaciones": "01-08-2007",
  "situacion_contribuyente": "ACTIVO",
  "fecha_ultimo_cambio": "01-08-2007",
  "regimen": "Régimen de Sueldos y Salarios e Ingresos Asimilados a Salarios",
  "fecha_alta": "01-08-2007",
  "entidad": "PUEBLA",
  "municipio": "OLINTLA",
  "colonia": "PUMACACHOCOCHUCHUT",
  "tipo_vialidad": "CALLE",
  "nombre_vialidad": "SIN NOMBRE",
  "numero_exterior": "46",
  "numero_interior": "",
  "cp": "73406",
  "correo": "",
  "al": "PUEBLA 1",
  "RFC_ETIQUETA": "GOGR890103AX8",
  "NOMBRE_ETIQUETA": "RAFAEL GOMEZ GOMEZ",
  "IDCIF_ETIQUETA": "23142054702"
}