{
  "D1": "10",
  "D2": "1",
  "D3": "24010481863_GUAV0510093A0",
  "rfc": "GUAV0510093A0",
  "curp": "GUAV051009MCMTDNA4",
  "nombre": "VIANCA JOSELINE",
  "apellido_paterno": "GUTIERREZ",
  "apellido_materno": "ADAME",
  "fecha_nacimiento": "",
  "fecha_inicio_operaciones": "",
  "situacion_contribuyente": "ACTIVO",
  "fecha_ultimo_cambio": "",
  "regimen": "Régimen de Sueldos y Salarios e Ingresos Asimilados a Salarios",
  "fecha_alta": "",
  "entidad": "BAJA CALIFORNIA",
  "municipio": "TIJUANA",
  "colonia": "LAS TORRES",
  "tipo_vialidad": "CALLE",
  "nombre_vialidad": "NOGAL",
  "numero_exterior": "21667",
  "numero_interior": "SIN NUMERO",
  "cp": "22470",
  "correo": "",
  "al": "",
  "RFC_ETIQUETA": "GUAV0510093A0",
  "NOMBRE_ETIQUETA": "VIANCA JOSELINE GUTIERREZ ADAME",
  "IDCIF_ETIQUETA": "24010481863"
}