{
  "D1": "10",
  "D2": "1",
  "D3": "24509334312_GURS540701H36",
  "rfc": "GURS540701H36",
  "curp": "GURS540701MJCRSM01",
  "nombre": "SIMONA",
  "apellido_paterno": "GUERRERO",
  "apellido_materno": "DE LA ROSA",
  "fecha_nacimiento": "01-07-1954",
  "fecha_inicio_operaciones": "17-03-1972",
  "situacion_contribuyente": "ACTIVO",
  "fecha_ultimo_cambio": "17-03-1972",
  "regimen": "Sin obligaciones fiscales",
  "fecha_alta": "17-03-1972",
  "entidad": "JALISCO",
  "municipio": "TALA",
  "colonia": "SAN IGNACIO DE CARBONERAS",
  "tipo_vialidad": "CALLE",
  "nombre_vialidad": "SIN NOMBRE",
  "numero_exterior": "",
  "numero_interior": "",
  "cp": "45349",
  "correo": "",
  "al": "JALISCO 1",
  "RFC_ETIQUETA": "GURS540701H36",
  "NOMBRE_ETIQUETA": "SIMONA GUERRERO DE LA ROSA",
  "IDCIF_ETIQUETA": "24509334312"
}