{
  "D1": "10",
  "D2": "1",
  "D3": "24597077060_HEGJ030207KI9",
  "rfc": "HEGJ030207KI9",
  "curp": "HEGJ030207HBCRRNA5",
  "nombre": "JUAN MARVIN",
  "apellido_paterno": "HERNANDEZ",
  "apellido_materno": "GARCIA",
  "fecha_nacimiento": "07-02-2003",
  "fecha_inicio_operaciones": "20-03-2021",
  "situacion_contribuyente": "ACTIVO",
  "fecha_ultimo_cambio": "20-03-2021",
  "regimen": "Régimen de Sueldos y Salarios e Ingresos Asimilados a Salarios",
  "fecha_alta": "20-03-2021",
  "entidad": "BAJA CALIFORNIA",
  "municipio": "TIJUANA",
  "colonia": "VILLAS DEL DORADO",
  "tipo_vialidad": "CALLE",
  "nombre_vialidad": "SIN NOMBRE",
  "numero_exterior": "471",
  "numero_interior": "",
  "cp": "22235",
  "correo": "",
  "al": "BAJA CALIFORNIA 1",
  "RFC_ETIQUETA": "HEGJ030207KI9",
  "NOMBRE_ETIQUETA": "JUAN MARVIN HERNANDEZ GARCIA",
  "IDCIF_ETIQUETA": "24597077060"
}