{
  "D1": "10",
  "D2": "1",
  "D3": "26030214236_TEJJ890916CU5",
  "rfc": "TEJJ890916CU5",
  "curp": "TEJJ890916HQTRVS01",
  "nombre": "JESUS DIONICIO",
  "apellido_paterno": "TREJO",
  "apellido_materno": "JAVIER",
  "fecha_nacimiento": "",
  "fecha_inicio_operaciones": "",
  "situacion_contribuyente": "ACTIVO",
  "fecha_ultimo_cambio": "",
  "regimen": "Régimen de Sueldos y Salarios e Ingresos Asimilados a Salarios",
  "fecha_alta": "",
  "entidad": "QUERETARO",
  "municipio": "QUERETARO",
  "colonia": "EL JACAL",
  "tipo_vialidad": "CALLE",
  "nombre_vialidad": "HACIENDA CHINTEPEC",
  "numero_exterior": "110",
  "numero_interior": "LOCAL 12",
  "cp": "76187",
  "correo": "",
  "al": "",
  "RFC_ETIQUETA": "TEJJ890916CU5",
  "NOMBRE_ETIQUETA": "JESUS DIONICIO TREJO JAVIER",
  "IDCIF_ETIQUETA": "26030214236"
}