{
  "D1": "10",
  "D2": "1",
  "D3": "26302882992_JIPJ9106054Y0",
  "rfc": "JIPJ9106054Y0",
  "curp": "JIPJ910605HTCMRN02",
  "nombre": "JUAN MANUEL",
  "apellido_paterno": "JIMENEZ",
  "apellido_materno": "PEREZ",
  "fecha_nacimiento": "05-06-1991",
  "fecha_inicio_operaciones": "30-04-2009",
  "situacion_contribuyente": "ACTIVO",
  "fecha_ultimo_cambio": "30-04-2009",
  "regimen": "Régimen de Sueldos y Salarios e Ingresos Asimilados a Salarios",
  "fecha_alta": "30-04-2009",
  "entidad": "TABASCO",
  "municipio": "PARAÍSO",
  "colonia": "LA UNIÓN 3RA. SECCIÓN",
  "tipo_vialidad": "CALLE",
  "nombre_vialidad": "SIN NOMBRE",
  "numero_exterior": "361",
  "numero_interior": "",
  "cp": "86618",
  "correo": "",
  "al": "TABASCO 1",
  "RFC_ETIQUETA": "JIPJ9106054Y0",
  "NOMBRE_ETIQUETA": "JUAN MANUEL JIMENEZ PEREZ",
  "IDCIF_ETIQUETA": "26302882992"
}