{
  "D1": "10",
  "D2": "1",
  "D3": "26317424330_REAJ010817QMA",
  "rfc": "REAJ010817QMA",
  "curp": "REAJ010817MMCYVNA5",
  "nombre": "JENNYFER",
  "apellido_paterno": "REYES",
  "apellido_materno": "AVALOS",
  "fecha_nacimiento": "17-08-2001",
  "fecha_inicio_operaciones": "27-12-2019",
  "situacion_contribuyente": "ACTIVO",
  "fecha_ultimo_cambio": "27-12-2019",
  "regimen": "Régimen de Sueldos y Salarios e Ingresos Asimilados a Salarios",
  "fecha_alta": "27-12-2019",
  "entidad": "MÉXICO",
  "municipio": "HUIXQUILUCAN",
  "colonia": "LA CIMA",
  "tipo_vialidad": "CALLE",
  "nombre_vialidad": "SIN NOMBRE",
  "numero_exterior": "64",
  "numero_interior": "",
  "cp": "52769",
  "correo": "",
  "al": "MÉXICO 1",
  "RFC_ETIQUETA": "REAJ010817QMA",
  "NOMBRE_ETIQUETA": "JENNYFER REYES AVALOS",
  "IDCIF_ETIQUETA": "26317424330"
}