{
  "D1": "10",
  "D2": "1",
  "D3": "26372736356_GASR930218LK4",
  "rfc": "GASR930218LK4",
  "curp": "GASR930218MJCRLS07",
  "nombre": "MARIA DEL ROSARIO",
  "apellido_paterno": "GARCIA",
  "apellido_materno": "SILVA",
  "fecha_nacimiento": "18-02-1993",
  "fecha_inicio_operaciones": "01-02-2011",
  "situacion_contribuyente": "ACTIVO",
  "fecha_ultimo_cambio": "01-02-2011",
  "regimen": "Régimen de Sueldos y Salarios e Ingresos Asimilados a Salarios",
  "fecha_alta": "01-02-2011",
  "entidad": "JALISCO",
  "municipio": "SAN PEDRO TLAQUEPAQUE",
  "colonia": "CANTO DE LUNA",
  "tipo_vialidad": "CALLE",
  "nombre_vialidad": "SIN NOMBRE",
  "numero_exterior": "313",
  "numero_interior": "",
  "cp": "45590",
  "correo": "",
  "al": "JALISCO 1",
  "RFC_ETIQUETA": "GASR930218LK4",
  "NOMBRE_ETIQUETA": "MARIA DEL ROSARIO GARCIA SILVA",
  "IDCIF_ETIQUETA": "26372736356"
}