{
  "D1": "10",
  "D2": "1",
  "D3": "26391834966_RAEF000507FT6",
  "rfc": "RAEF000507FT6",
  "curp": "RAEF000507HGTZSRA1",
  "nombre": "FRANCISCO FELIPE",
  "apellido_paterno": "RAZO",
  "apellido_materno": "ESPARZA",
  "fecha_nacimiento": "07-05-2000",
  "fecha_inicio_operaciones": "03-01-2018",
  "situacion_contribuyente": "ACTIVO",
  "fecha_ultimo_cambio": "03-01-2018",
  "regimen": "Régimen de Sueldos y Salarios e Ingresos Asimilados a Salarios",
  "fecha_alta": "03-01-2018",
  "entidad": "GUANAJUATO",
  "municipio": "LEÓN",
  "colonia": "FUTURAMA MONTERREY",
  "tipo_vialidad": "CALLE",
  "nombre_vialidad": "SIN NOMBRE",
  "numero_exterior": "363",
  "numero_interior": "",
  "cp": "37180",
  "correo": "",
  "al": "GUANAJUATO 1",
  "RFC_ETIQUETA": "RAEF000507FT6",
  "NOMBRE_ETIQUETA": "FRANCISCO FELIPE RAZO ESPARZA",
  "IDCIF_ETIQUETA": "26391834966"
}