{
  "D1": "10",
  "D2": "1",
  "D3": "27000369525_RACV8008228H1",
  "rfc": "RACV8008228H1",
  "curp": "RACV800822HJCMRC07",
  "nombre": "VICTOR EDUARDO",
  "apellido_paterno": "RAMOS",
  "apellido_materno": "CERVANTES",
  "fecha_nacimiento": "22-08-1980",
  "fecha_inicio_operaciones": "22-05-1998",
  "situacion_contribuyente": "ACTIVO",
  "fecha_ultimo_cambio": "22-05-1998",
  "regimen": "Régimen de Sueldos y Salarios e Ingresos Asimilados a Salarios",
  "fecha_alta": "22-05-1998",
  "entidad": "JALISCO",
  "municipio": "GUADALAJARA",
  "colonia": "SAN ANTONIO",
  "tipo_vialidad": "CALLE",
  "nombre_vialidad": "SIN NOMBRE",
  "numero_exterior": "166",
  "numero_interior": "",
  "cp": "44257",
  "correo": "",
  "al": "JALISCO 1",
  "RFC_ETIQUETA": "RACV8008228H1",
  "NOMBRE_ETIQUETA": "VICTOR EDUARDO RAMOS CERVANTES",
  "IDCIF_ETIQUETA": "27000369525"
}