{
  "D1": "10",
  "D2": "1",
  "D3": "27265537423_SAFN970820568",
  "rfc": "SAFN970820568",
  "curp": "SAFN970820MMCNLY02",
  "nombre": "NAYELLI SARAI",
  "apellido_paterno": "SANTOS",
  "apellido_materno": "FLORES",
  "fecha_nacimiento": "20-08-1997",
  "fecha_inicio_operaciones": "19-12-2015",
  "situacion_contribuyente": "ACTIVO",
  "fecha_ultimo_cambio": "19-12-2015",
  "regimen": "Régimen de Sueldos y Salarios e Ingresos Asimilados a Salarios",
  "fecha_alta": "19-12-2015",
  "entidad": "MÉXICO",
  "municipio": "CUAUTITLÁN",
  "colonia": "TECOAC-MONALES",
  "tipo_vialidad": "CALLE",
  "nombre_vialidad": "SIN NOMBRE",
  "numero_exterior": "69",
  "numero_interior": "",
  "cp": "54804",
  "correo": "",
  "al": "MÉXICO 1",
  "RFC_ETIQUETA": "SAFN970820568",
  "NOMBRE_ETIQUETA": "NAYELLI SARAI SANTOS FLORES",
  "IDCIF_ETIQUETA": "27265537423"
}