{
  "D1": "10",
  "D2": "1",
  "D3": "27633615336_NAIE730313753",
  "rfc": "NAIE730313753",
  "curp": "NAIE730313HNLVBD05",
  "nombre": "EDUARDO",
  "apellido_paterno": "NAVARRO",
  "apellido_materno": "IBARRA",
  "fecha_nacimiento": "13-03-1973",
  "fecha_inicio_operaciones": "12-09-1989",
  "situacion_contribuyente": "ACTIVO",
  "fecha_ultimo_cambio": "12-09-1989",
  "regimen": "Régimen de las Personas Físicas con Actividades Empresariales y Profesionales",
  "fecha_alta": "12-09-1989",
  "entidad": "QUINTANA ROO",
  "municipio": "BENITO JUÁREZ",
  "colonia": "BOSQUES SAN MIGUEL",
  "tipo_vialidad": "CALLE",
  "nombre_vialidad": "SIN NOMBRE",
  "numero_exterior": "551",
  "numero_interior": "",
  "cp": "77535",
  "correo": "",
  "al": "QUINTANA ROO 1",
  "RFC_ETIQUETA": "NAIE730313753",
  "NOMBRE_ETIQUETA": "EDUARDO NAVARRO IBARRA",
  "IDCIF_ETIQUETA": "27633615336"
}