{
  "D1": "10",
  "D2": "1",
  "D3": "28253229274_NORJ740109BI6",
  "rfc": "NORJ740109BI6",
  "curp": "NORJ740109HDFRZL02",
  "nombre": "JULIAN",
  "apellido_paterno": "NORIEGA",
  "apellido_materno": "RAZO",
  "fecha_nacimiento": "09-01-1974",
  "fecha_inicio_operaciones": "03-12-1992",
  "situacion_contribuyente": "ACTIVO",
  "fecha_ultimo_cambio": "03-12-1992",
  "regimen": "Régimen de Sueldos y Salarios e Ingresos Asimilados a Salarios",
  "fecha_alta": "03-12-1992",
  "entidad": "MÉXICO",
  "municipio": "ECATEPEC DE MORELOS",
  "colonia": "19 DE SEPTIEMBRE",
  "tipo_vialidad": "CALLE",
  "nombre_vialidad": "SIN NOMBRE",
  "numero_exterior": "624",
  "numero_interior": "",
  "cp": "55070",
  "correo": "",
  "al": "MÉXICO 1",
  "RFC_ETIQUETA": "NORJ740109BI6",
  "NOMBRE_ETIQUETA": "JULIAN NORIEGA RAZO",
  "IDCIF_ETIQUETA": "28253229274"
}